<?xml version="1.0" encoding="utf-8"?>
<networx-backup>
  <data>
    <item>
      <user>dufferzafar</user>
      <day>41457</day>
      <in>13486769</in>
      <out>3347951</out>
      <dialup>1636</dialup>
      <hour>20</hour>
    </item>
    <item>
      <user>dufferzafar</user>
      <day>41457</day>
      <in>9180421</in>
      <out>1001053</out>
      <dialup>478</dialup>
      <hour>21</hour>
    </item>
    <item>
      <user>dufferzafar</user>
      <day>41457</day>
      <in>145156</in>
      <out>86068</out>
      <dialup>75</dialup>
      <hour>23</hour>
    </item>
    <item>
      <user>dufferzafar</user>
      <day>41458</day>
      <in>37924836</in>
      <out>3600826</out>
      <dialup>2339</dialup>
      <hour>22</hour>
    </item>
    <item>
      <user>dufferzafar</user>
      <day>41458</day>
      <in>0</in>
      <out>2175</out>
      <dialup>3</dialup>
      <hour>23</hour>
    </item>
    <item>
      <user>dufferzafar</user>
      <day>41459</day>
      <in>12257020</in>
      <out>1046737</out>
      <dialup>690</dialup>
      <hour>6</hour>
    </item>
    <item>
      <user>dufferzafar</user>
      <day>41459</day>
      <in>10576087</in>
      <out>4005737</out>
      <dialup>1550</dialup>
      <hour>20</hour>
    </item>
    <item>
      <user>dufferzafar</user>
      <day>41459</day>
      <in>22931607</in>
      <out>8754843</out>
      <dialup>3550</dialup>
      <hour>21</hour>
    </item>
    <item>
      <user>dufferzafar</user>
      <day>41459</day>
      <in>11245873</in>
      <out>4879021</out>
      <dialup>1653</dialup>
      <hour>22</hour>
    </item>
    <item>
      <user>dufferzafar</user>
      <day>41460</day>
      <in>25468984</in>
      <out>5436880</out>
      <dialup>2292</dialup>
      <hour>14</hour>
    </item>
    <item>
      <user>dufferzafar</user>
      <day>41460</day>
      <in>14729868</in>
      <out>2679858</out>
      <dialup>3031</dialup>
      <hour>17</hour>
    </item>
    <item>
      <user>dufferzafar</user>
      <day>41460</day>
      <in>9715938</in>
      <out>1257395</out>
      <dialup>3541</dialup>
      <hour>18</hour>
    </item>
    <item>
      <user>dufferzafar</user>
      <day>41460</day>
      <in>24595430</in>
      <out>1193501</out>
      <dialup>987</dialup>
      <hour>19</hour>
    </item>
    <item>
      <user>dufferzafar</user>
      <day>41461</day>
      <in>7955092</in>
      <out>1337292</out>
      <dialup>1663</dialup>
      <hour>13</hour>
    </item>
    <item>
      <user>dufferzafar</user>
      <day>41461</day>
      <in>114014</in>
      <out>67206</out>
      <dialup>3551</dialup>
      <hour>14</hour>
    </item>
    <item>
      <user>dufferzafar</user>
      <day>41461</day>
      <in>39383682</in>
      <out>8396125</out>
      <dialup>3550</dialup>
      <hour>15</hour>
    </item>
    <item>
      <user>dufferzafar</user>
      <day>41461</day>
      <in>9085303</in>
      <out>1874244</out>
      <dialup>1459</dialup>
      <hour>16</hour>
    </item>
    <item>
      <user>dufferzafar</user>
      <day>41461</day>
      <in>7135069</in>
      <out>1417836</out>
      <dialup>1101</dialup>
      <hour>21</hour>
    </item>
    <item>
      <user>dufferzafar</user>
      <day>41461</day>
      <in>22179218</in>
      <out>5830030</out>
      <dialup>3429</dialup>
      <hour>22</hour>
    </item>
    <item>
      <user>dufferzafar</user>
      <day>41461</day>
      <in>15005355</in>
      <out>9443420</out>
      <dialup>3550</dialup>
      <hour>23</hour>
    </item>
    <item>
      <user>dufferzafar</user>
      <day>41462</day>
      <in>26912722</in>
      <out>3282210</out>
      <dialup>1670</dialup>
      <hour>0</hour>
    </item>
    <item>
      <user>dufferzafar</user>
      <day>41462</day>
      <in>24830123</in>
      <out>2966270</out>
      <dialup>2335</dialup>
      <hour>18</hour>
    </item>
    <item>
      <user>dufferzafar</user>
      <day>41462</day>
      <in>15277080</in>
      <out>6932342</out>
      <dialup>1853</dialup>
      <hour>19</hour>
    </item>
    <item>
      <user>dufferzafar</user>
      <day>41462</day>
      <in>4192187</in>
      <out>831208</out>
      <dialup>348</dialup>
      <hour>21</hour>
    </item>
    <item>
      <user>dufferzafar</user>
      <day>41462</day>
      <in>11525047</in>
      <out>2199282</out>
      <dialup>3551</dialup>
      <hour>22</hour>
    </item>
    <item>
      <user>dufferzafar</user>
      <day>41462</day>
      <in>6993262</in>
      <out>1214797</out>
      <dialup>3550</dialup>
      <hour>23</hour>
    </item>
    <item>
      <user>dufferzafar</user>
      <day>41463</day>
      <in>4380572</in>
      <out>712456</out>
      <dialup>902</dialup>
      <hour>0</hour>
    </item>
    <item>
      <user>dufferzafar</user>
      <day>41463</day>
      <in>10941886</in>
      <out>3065372</out>
      <dialup>2113</dialup>
      <hour>10</hour>
    </item>
    <item>
      <user>dufferzafar</user>
      <day>41463</day>
      <in>1959108</in>
      <out>1080029</out>
      <dialup>3550</dialup>
      <hour>11</hour>
    </item>
    <item>
      <user>dufferzafar</user>
      <day>41463</day>
      <in>13369688</in>
      <out>2872480</out>
      <dialup>3551</dialup>
      <hour>12</hour>
    </item>
    <item>
      <user>dufferzafar</user>
      <day>41463</day>
      <in>1126632</in>
      <out>374772</out>
      <dialup>3550</dialup>
      <hour>13</hour>
    </item>
    <item>
      <user>dufferzafar</user>
      <day>41463</day>
      <in>2138953</in>
      <out>376076</out>
      <dialup>3550</dialup>
      <hour>14</hour>
    </item>
    <item>
      <user>dufferzafar</user>
      <day>41463</day>
      <in>28429424</in>
      <out>3522502</out>
      <dialup>3551</dialup>
      <hour>15</hour>
    </item>
    <item>
      <user>dufferzafar</user>
      <day>41463</day>
      <in>3396045</in>
      <out>737033</out>
      <dialup>380</dialup>
      <hour>16</hour>
    </item>
    <item>
      <user>dufferzafar</user>
      <day>41463</day>
      <in>8798081</in>
      <out>2167958</out>
      <dialup>2005</dialup>
      <hour>20</hour>
    </item>
    <item>
      <user>dufferzafar</user>
      <day>41463</day>
      <in>11508389</in>
      <out>2459057</out>
      <dialup>3550</dialup>
      <hour>21</hour>
    </item>
    <item>
      <user>dufferzafar</user>
      <day>41463</day>
      <in>2193543</in>
      <out>1481309</out>
      <dialup>3550</dialup>
      <hour>22</hour>
    </item>
    <item>
      <user>dufferzafar</user>
      <day>41463</day>
      <in>33552432</in>
      <out>4537476</out>
      <dialup>3550</dialup>
      <hour>23</hour>
    </item>
    <item>
      <user>dufferzafar</user>
      <day>41464</day>
      <in>11388416</in>
      <out>3758851</out>
      <dialup>3551</dialup>
      <hour>0</hour>
    </item>
    <item>
      <user>dufferzafar</user>
      <day>41464</day>
      <in>22776028</in>
      <out>5347007</out>
      <dialup>3550</dialup>
      <hour>1</hour>
    </item>
    <item>
      <user>dufferzafar</user>
      <day>41464</day>
      <in>8177364</in>
      <out>5264658</out>
      <dialup>2578</dialup>
      <hour>2</hour>
    </item>
    <item>
      <user>dufferzafar</user>
      <day>41464</day>
      <in>2162901</in>
      <out>532418</out>
      <dialup>367</dialup>
      <hour>8</hour>
    </item>
    <item>
      <user>dufferzafar</user>
      <day>41464</day>
      <in>9005114</in>
      <out>814469</out>
      <dialup>3550</dialup>
      <hour>9</hour>
    </item>
    <item>
      <user>dufferzafar</user>
      <day>41464</day>
      <in>3134066</in>
      <out>543197</out>
      <dialup>1994</dialup>
      <hour>10</hour>
    </item>
    <item>
      <user>dufferzafar</user>
      <day>41464</day>
      <in>10106826</in>
      <out>2467986</out>
      <dialup>1890</dialup>
      <hour>11</hour>
    </item>
    <item>
      <user>dufferzafar</user>
      <day>41464</day>
      <in>2679285</in>
      <out>370981</out>
      <dialup>180</dialup>
      <hour>19</hour>
    </item>
    <item>
      <user>dufferzafar</user>
      <day>41464</day>
      <in>14614574</in>
      <out>3767338</out>
      <dialup>3550</dialup>
      <hour>20</hour>
    </item>
    <item>
      <user>dufferzafar</user>
      <day>41464</day>
      <in>13439804</in>
      <out>17900758</out>
      <dialup>3550</dialup>
      <hour>21</hour>
    </item>
    <item>
      <user>dufferzafar</user>
      <day>41464</day>
      <in>2315835</in>
      <out>3631504</out>
      <dialup>1056</dialup>
      <hour>22</hour>
    </item>
    <item>
      <user>dufferzafar</user>
      <day>41464</day>
      <in>4853196</in>
      <out>726806</out>
      <dialup>2302</dialup>
      <hour>23</hour>
    </item>
    <item>
      <user>dufferzafar</user>
      <day>41465</day>
      <in>10594476</in>
      <out>1512442</out>
      <dialup>1066</dialup>
      <hour>10</hour>
    </item>
    <item>
      <user>dufferzafar</user>
      <day>41465</day>
      <in>17496629</in>
      <out>2912438</out>
      <dialup>3550</dialup>
      <hour>11</hour>
    </item>
    <item>
      <user>dufferzafar</user>
      <day>41465</day>
      <in>1917670</in>
      <out>293727</out>
      <dialup>1296</dialup>
      <hour>12</hour>
    </item>
    <item>
      <user>dufferzafar</user>
      <day>41465</day>
      <in>6632770</in>
      <out>3591653</out>
      <dialup>1644</dialup>
      <hour>13</hour>
    </item>
    <item>
      <user>dufferzafar</user>
      <day>41465</day>
      <in>3089828</in>
      <out>2119676</out>
      <dialup>604</dialup>
      <hour>14</hour>
    </item>
    <item>
      <user>dufferzafar</user>
      <day>41465</day>
      <in>2259204</in>
      <out>1200578</out>
      <dialup>743</dialup>
      <hour>15</hour>
    </item>
    <item>
      <user>dufferzafar</user>
      <day>41465</day>
      <in>0</in>
      <out>2115</out>
      <dialup>0</dialup>
      <hour>16</hour>
    </item>
    <item>
      <user>dufferzafar</user>
      <day>41465</day>
      <in>3539162</in>
      <out>611746</out>
      <dialup>244</dialup>
      <hour>18</hour>
    </item>
    <item>
      <user>dufferzafar</user>
      <day>41465</day>
      <in>44318452</in>
      <out>18976404</out>
      <dialup>3551</dialup>
      <hour>19</hour>
    </item>
    <item>
      <user>dufferzafar</user>
      <day>41465</day>
      <in>7283811</in>
      <out>2775506</out>
      <dialup>2519</dialup>
      <hour>20</hour>
    </item>
    <item>
      <user>dufferzafar</user>
      <day>41466</day>
      <in>8574957</in>
      <out>1744356</out>
      <dialup>936</dialup>
      <hour>12</hour>
    </item>
    <item>
      <user>dufferzafar</user>
      <day>41466</day>
      <in>1260212</in>
      <out>656328</out>
      <dialup>3170</dialup>
      <hour>13</hour>
    </item>
    <item>
      <user>dufferzafar</user>
      <day>41466</day>
      <in>16790425</in>
      <out>2558454</out>
      <dialup>3550</dialup>
      <hour>14</hour>
    </item>
    <item>
      <user>dufferzafar</user>
      <day>41466</day>
      <in>6206243</in>
      <out>1623801</out>
      <dialup>1133</dialup>
      <hour>15</hour>
    </item>
    <item>
      <user>dufferzafar</user>
      <day>41466</day>
      <in>28007611</in>
      <out>3886064</out>
      <dialup>2623</dialup>
      <hour>16</hour>
    </item>
    <item>
      <user>dufferzafar</user>
      <day>41466</day>
      <in>35699340</in>
      <out>5006419</out>
      <dialup>3551</dialup>
      <hour>17</hour>
    </item>
    <item>
      <user>dufferzafar</user>
      <day>41466</day>
      <in>249541</in>
      <out>1471793</out>
      <dialup>488</dialup>
      <hour>18</hour>
    </item>
    <item>
      <user>dufferzafar</user>
      <day>41467</day>
      <in>23288594</in>
      <out>1984137</out>
      <dialup>959</dialup>
      <hour>12</hour>
    </item>
    <item>
      <user>dufferzafar</user>
      <day>41467</day>
      <in>8662041</in>
      <out>493441</out>
      <dialup>238</dialup>
      <hour>13</hour>
    </item>
    <item>
      <user>dufferzafar</user>
      <day>41467</day>
      <in>9564894</in>
      <out>1843732</out>
      <dialup>1682</dialup>
      <hour>14</hour>
    </item>
    <item>
      <user>dufferzafar</user>
      <day>41467</day>
      <in>32053939</in>
      <out>12746619</out>
      <dialup>2269</dialup>
      <hour>15</hour>
    </item>
    <item>
      <user>dufferzafar</user>
      <day>41467</day>
      <in>16146518</in>
      <out>2541900</out>
      <dialup>1373</dialup>
      <hour>17</hour>
    </item>
    <item>
      <user>dufferzafar</user>
      <day>41467</day>
      <in>23173023</in>
      <out>2907806</out>
      <dialup>1626</dialup>
      <hour>20</hour>
    </item>
    <item>
      <user>dufferzafar</user>
      <day>41467</day>
      <in>32692176</in>
      <out>10687382</out>
      <dialup>3550</dialup>
      <hour>21</hour>
    </item>
    <item>
      <user>dufferzafar</user>
      <day>41467</day>
      <in>20479234</in>
      <out>12820805</out>
      <dialup>3550</dialup>
      <hour>22</hour>
    </item>
    <item>
      <user>dufferzafar</user>
      <day>41467</day>
      <in>19866055</in>
      <out>3555935</out>
      <dialup>1539</dialup>
      <hour>23</hour>
    </item>
    <item>
      <user>dufferzafar</user>
      <day>41471</day>
      <in>28499661</in>
      <out>16198385</out>
      <dialup>3162</dialup>
      <hour>20</hour>
    </item>
    <item>
      <user>dufferzafar</user>
      <day>41471</day>
      <in>17887933</in>
      <out>1245641</out>
      <dialup>3533</dialup>
      <hour>21</hour>
    </item>
    <item>
      <user>dufferzafar</user>
      <day>41471</day>
      <in>14877706</in>
      <out>2517825</out>
      <dialup>3551</dialup>
      <hour>22</hour>
    </item>
    <item>
      <user>dufferzafar</user>
      <day>41471</day>
      <in>4178673</in>
      <out>1227067</out>
      <dialup>1848</dialup>
      <hour>23</hour>
    </item>
    <item>
      <user>dufferzafar</user>
      <day>41472</day>
      <in>19612651</in>
      <out>11439176</out>
      <dialup>2693</dialup>
      <hour>20</hour>
    </item>
    <item>
      <user>dufferzafar</user>
      <day>41472</day>
      <in>4085215</in>
      <out>580416</out>
      <dialup>3551</dialup>
      <hour>21</hour>
    </item>
    <item>
      <user>dufferzafar</user>
      <day>41472</day>
      <in>13829420</in>
      <out>4268143</out>
      <dialup>3541</dialup>
      <hour>22</hour>
    </item>
    <item>
      <user>dufferzafar</user>
      <day>41472</day>
      <in>2975424</in>
      <out>689038</out>
      <dialup>936</dialup>
      <hour>23</hour>
    </item>
    <item>
      <user>dufferzafar</user>
      <day>41473</day>
      <in>15452028</in>
      <out>2531631</out>
      <dialup>2552</dialup>
      <hour>16</hour>
    </item>
    <item>
      <user>dufferzafar</user>
      <day>41473</day>
      <in>16216175</in>
      <out>1852985</out>
      <dialup>3551</dialup>
      <hour>17</hour>
    </item>
    <item>
      <user>dufferzafar</user>
      <day>41473</day>
      <in>32519526</in>
      <out>3634090</out>
      <dialup>3210</dialup>
      <hour>18</hour>
    </item>
    <item>
      <user>dufferzafar</user>
      <day>41473</day>
      <in>3953749</in>
      <out>703719</out>
      <dialup>1031</dialup>
      <hour>19</hour>
    </item>
    <item>
      <user>dufferzafar</user>
      <day>41473</day>
      <in>23756810</in>
      <out>3460892</out>
      <dialup>2947</dialup>
      <hour>20</hour>
    </item>
    <item>
      <user>dufferzafar</user>
      <day>41473</day>
      <in>1817005</in>
      <out>15902391</out>
      <dialup>2182</dialup>
      <hour>21</hour>
    </item>
    <item>
      <user>dufferzafar</user>
      <day>41474</day>
      <in>13041417</in>
      <out>3997535</out>
      <dialup>3350</dialup>
      <hour>16</hour>
    </item>
    <item>
      <user>dufferzafar</user>
      <day>41474</day>
      <in>9000197</in>
      <out>778068</out>
      <dialup>3550</dialup>
      <hour>17</hour>
    </item>
    <item>
      <user>dufferzafar</user>
      <day>41474</day>
      <in>13863247</in>
      <out>1777512</out>
      <dialup>1168</dialup>
      <hour>18</hour>
    </item>
    <item>
      <user>dufferzafar</user>
      <day>41474</day>
      <in>271859</in>
      <out>67254</out>
      <dialup>13</dialup>
      <hour>19</hour>
    </item>
    <item>
      <user>dufferzafar</user>
      <day>41474</day>
      <in>8133122</in>
      <out>2051684</out>
      <dialup>3092</dialup>
      <hour>21</hour>
    </item>
    <item>
      <user>dufferzafar</user>
      <day>41474</day>
      <in>2781885</in>
      <out>810855</out>
      <dialup>3550</dialup>
      <hour>22</hour>
    </item>
    <item>
      <user>dufferzafar</user>
      <day>41474</day>
      <in>28300618</in>
      <out>4914017</out>
      <dialup>3550</dialup>
      <hour>23</hour>
    </item>
    <item>
      <user>dufferzafar</user>
      <day>41475</day>
      <in>30199807</in>
      <out>5656719</out>
      <dialup>3550</dialup>
      <hour>0</hour>
    </item>
    <item>
      <user>dufferzafar</user>
      <day>41475</day>
      <in>16672597</in>
      <out>3790018</out>
      <dialup>2439</dialup>
      <hour>1</hour>
    </item>
    <item>
      <user>dufferzafar</user>
      <day>41475</day>
      <in>11917330</in>
      <out>1891420</out>
      <dialup>1757</dialup>
      <hour>12</hour>
    </item>
    <item>
      <user>dufferzafar</user>
      <day>41475</day>
      <in>619131</in>
      <out>112859</out>
      <dialup>3551</dialup>
      <hour>13</hour>
    </item>
    <item>
      <user>dufferzafar</user>
      <day>41475</day>
      <in>4985869</in>
      <out>1033444</out>
      <dialup>3550</dialup>
      <hour>14</hour>
    </item>
    <item>
      <user>dufferzafar</user>
      <day>41475</day>
      <in>18162</in>
      <out>17127</out>
      <dialup>3550</dialup>
      <hour>15</hour>
    </item>
    <item>
      <user>dufferzafar</user>
      <day>41475</day>
      <in>2247688</in>
      <out>524375</out>
      <dialup>3550</dialup>
      <hour>16</hour>
    </item>
    <item>
      <user>dufferzafar</user>
      <day>41475</day>
      <in>2525765</in>
      <out>411603</out>
      <dialup>3346</dialup>
      <hour>17</hour>
    </item>
    <item>
      <user>dufferzafar</user>
      <day>41476</day>
      <in>8466758</in>
      <out>6557728</out>
      <dialup>2340</dialup>
      <hour>10</hour>
    </item>
    <item>
      <user>dufferzafar</user>
      <day>41476</day>
      <in>3034641</in>
      <out>5817233</out>
      <dialup>3550</dialup>
      <hour>11</hour>
    </item>
    <item>
      <user>dufferzafar</user>
      <day>41476</day>
      <in>320284</in>
      <out>291215</out>
      <dialup>3551</dialup>
      <hour>12</hour>
    </item>
    <item>
      <user>dufferzafar</user>
      <day>41476</day>
      <in>14464019</in>
      <out>1126477</out>
      <dialup>3550</dialup>
      <hour>13</hour>
    </item>
    <item>
      <user>dufferzafar</user>
      <day>41476</day>
      <in>7114399</in>
      <out>493193</out>
      <dialup>412</dialup>
      <hour>14</hour>
    </item>
    <item>
      <user>dufferzafar</user>
      <day>41476</day>
      <in>1808231</in>
      <out>351778</out>
      <dialup>2268</dialup>
      <hour>17</hour>
    </item>
    <item>
      <user>dufferzafar</user>
      <day>41476</day>
      <in>691093</in>
      <out>204105</out>
      <dialup>124</dialup>
      <hour>19</hour>
    </item>
    <item>
      <user>dufferzafar</user>
      <day>41476</day>
      <in>12583050</in>
      <out>4053204</out>
      <dialup>3550</dialup>
      <hour>20</hour>
    </item>
    <item>
      <user>dufferzafar</user>
      <day>41476</day>
      <in>8241941</in>
      <out>1458018</out>
      <dialup>1933</dialup>
      <hour>21</hour>
    </item>
    <item>
      <user>dufferzafar</user>
      <day>41477</day>
      <in>14148966</in>
      <out>2676771</out>
      <dialup>1144</dialup>
      <hour>16</hour>
    </item>
    <item>
      <user>dufferzafar</user>
      <day>41477</day>
      <in>17331650</in>
      <out>1647940</out>
      <dialup>3550</dialup>
      <hour>17</hour>
    </item>
    <item>
      <user>dufferzafar</user>
      <day>41477</day>
      <in>11609672</in>
      <out>1485698</out>
      <dialup>3550</dialup>
      <hour>18</hour>
    </item>
    <item>
      <user>dufferzafar</user>
      <day>41477</day>
      <in>2252693</in>
      <out>327654</out>
      <dialup>642</dialup>
      <hour>19</hour>
    </item>
    <item>
      <user>dufferzafar</user>
      <day>41478</day>
      <in>12984669</in>
      <out>3671492</out>
      <dialup>1966</dialup>
      <hour>17</hour>
    </item>
    <item>
      <user>dufferzafar</user>
      <day>41478</day>
      <in>5700337</in>
      <out>512906</out>
      <dialup>3550</dialup>
      <hour>18</hour>
    </item>
    <item>
      <user>dufferzafar</user>
      <day>41478</day>
      <in>14637543</in>
      <out>1067294</out>
      <dialup>1124</dialup>
      <hour>19</hour>
    </item>
    <item>
      <user>dufferzafar</user>
      <day>41478</day>
      <in>17882084</in>
      <out>2520399</out>
      <dialup>2311</dialup>
      <hour>20</hour>
    </item>
    <item>
      <user>dufferzafar</user>
      <day>41478</day>
      <in>1677096</in>
      <out>314974</out>
      <dialup>695</dialup>
      <hour>21</hour>
    </item>
    <item>
      <user>dufferzafar</user>
      <day>41478</day>
      <in>22199548</in>
      <out>4536067</out>
      <dialup>2752</dialup>
      <hour>22</hour>
    </item>
    <item>
      <user>dufferzafar</user>
      <day>41478</day>
      <in>8491465</in>
      <out>1433454</out>
      <dialup>569</dialup>
      <hour>23</hour>
    </item>
    <item>
      <user>dufferzafar</user>
      <day>41479</day>
      <in>32910846</in>
      <out>5256882</out>
      <dialup>2776</dialup>
      <hour>20</hour>
    </item>
    <item>
      <user>dufferzafar</user>
      <day>41479</day>
      <in>11894156</in>
      <out>25384193</out>
      <dialup>3551</dialup>
      <hour>21</hour>
    </item>
    <item>
      <user>dufferzafar</user>
      <day>41479</day>
      <in>4721291</in>
      <out>12306266</out>
      <dialup>2703</dialup>
      <hour>22</hour>
    </item>
    <item>
      <user>dufferzafar</user>
      <day>41480</day>
      <in>11001401</in>
      <out>1892247</out>
      <dialup>1541</dialup>
      <hour>17</hour>
    </item>
    <item>
      <user>dufferzafar</user>
      <day>41480</day>
      <in>17350464</in>
      <out>3428023</out>
      <dialup>3551</dialup>
      <hour>18</hour>
    </item>
    <item>
      <user>dufferzafar</user>
      <day>41480</day>
      <in>900329</in>
      <out>162293</out>
      <dialup>904</dialup>
      <hour>19</hour>
    </item>
    <item>
      <user>dufferzafar</user>
      <day>41480</day>
      <in>2375229</in>
      <out>611156</out>
      <dialup>298</dialup>
      <hour>20</hour>
    </item>
    <item>
      <user>dufferzafar</user>
      <day>41480</day>
      <in>9700962</in>
      <out>14128284</out>
      <dialup>3550</dialup>
      <hour>21</hour>
    </item>
    <item>
      <user>dufferzafar</user>
      <day>41480</day>
      <in>26742234</in>
      <out>65229276</out>
      <dialup>2841</dialup>
      <hour>22</hour>
    </item>
    <item>
      <user>dufferzafar</user>
      <day>41484</day>
      <in>50838</in>
      <out>170957</out>
      <dialup>705</dialup>
      <hour>18</hour>
    </item>
    <item>
      <user>dufferzafar</user>
      <day>41484</day>
      <in>0</in>
      <out>0</out>
      <dialup>14</dialup>
      <hour>19</hour>
    </item>
    <item>
      <user>dufferzafar</user>
      <day>41489</day>
      <in>16876498</in>
      <out>1597461</out>
      <dialup>598</dialup>
      <hour>16</hour>
    </item>
  </data>
  <dialup>
    <item>
      <connection>MBlaze USB Modem</connection>
      <since>2013-07-02 20:10:54</since>
      <duration>426</duration>
      <in>4475115</in>
      <out>379471</out>
    </item>
    <item>
      <connection>MBlaze USB Modem</connection>
      <since>2013-07-02 20:37:23</since>
      <duration>1866</duration>
      <in>20375984</in>
      <out>2683234</out>
    </item>
    <item>
      <connection>MBlaze USB Modem</connection>
      <since>2013-07-02 21:09:56</since>
      <duration>53</duration>
      <in>46066</in>
      <out>37206</out>
    </item>
    <item>
      <connection>MBlaze USB Modem</connection>
      <since>2013-07-03 22:12:34</since>
      <duration>2375</duration>
      <in>37553369</in>
      <out>3701075</out>
    </item>
    <item>
      <connection>MBlaze USB Modem</connection>
      <since>2013-07-04 06:21:31</since>
      <duration>702</duration>
      <in>12138512</in>
      <out>1086345</out>
    </item>
    <item>
      <connection>MBlaze USB Modem</connection>
      <since>2013-07-04 20:33:34</since>
      <duration>6850</duration>
      <in>50052726</in>
      <out>11704829</out>
    </item>
    <item>
      <connection>MBlaze USB Modem</connection>
      <since>2013-07-05 14:02:13</since>
      <duration>2326</duration>
      <in>27359956</in>
      <out>3496260</out>
    </item>
    <item>
      <connection>MBlaze USB Modem</connection>
      <since>2013-07-05 17:08:25</since>
      <duration>30</duration>
      <in>386284</in>
      <out>131428</out>
    </item>
    <item>
      <connection>MBlaze USB Modem</connection>
      <since>2013-07-05 17:08:58</since>
      <duration>5002</duration>
      <in>14736559</in>
      <out>2773596</out>
    </item>
    <item>
      <connection>MBlaze USB Modem</connection>
      <since>2013-07-05 18:32:28</since>
      <duration>2648</duration>
      <in>33667243</in>
      <out>2321656</out>
    </item>
    <item>
      <connection>MBlaze USB Modem</connection>
      <since>2013-07-06 13:31:51</since>
      <duration>10207</duration>
      <in>59545294</in>
      <out>6249805</out>
    </item>
    <item>
      <connection>MBlaze USB Modem</connection>
      <since>2013-07-06 16:35:45</since>
      <duration>156</duration>
      <in>1281269</in>
      <out>372882</out>
    </item>
    <item>
      <connection>MBlaze USB Modem</connection>
      <since>2013-07-06 21:41:17</since>
      <duration>3388</duration>
      <in>19500226</in>
      <out>2796480</out>
    </item>
    <item>
      <connection>MBlaze USB Modem</connection>
      <since>2013-07-06 22:39:55</since>
      <duration>6470</duration>
      <in>58046215</in>
      <out>10359253</out>
    </item>
    <item>
      <connection>MBlaze USB Modem</connection>
      <since>2013-07-07 18:20:26</since>
      <duration>4236</duration>
      <in>44074237</in>
      <out>5496719</out>
    </item>
    <item>
      <connection>MBlaze USB Modem</connection>
      <since>2013-07-07 21:54:03</since>
      <duration>8445</duration>
      <in>26768103</in>
      <out>4906629</out>
    </item>
    <item>
      <connection>MBlaze USB Modem</connection>
      <since>2013-07-08 10:24:10</since>
      <duration>20499</duration>
      <in>62557437</in>
      <out>10352829</out>
    </item>
    <item>
      <connection>MBlaze USB Modem</connection>
      <since>2013-07-08 20:25:44</since>
      <duration>38</duration>
      <in>419102</in>
      <out>142578</out>
    </item>
    <item>
      <connection>MBlaze USB Modem</connection>
      <since>2013-07-08 20:26:25</since>
      <duration>22596</duration>
      <in>100458477</in>
      <out>21487789</out>
    </item>
    <item>
      <connection>MBlaze USB Modem</connection>
      <since>2013-07-09 08:53:36</since>
      <duration>5875</duration>
      <in>14070728</in>
      <out>1841855</out>
    </item>
    <item>
      <connection>MBlaze USB Modem</connection>
      <since>2013-07-09 10:31:43</since>
      <duration>160</duration>
      <in>115707</in>
      <out>44082</out>
    </item>
    <item>
      <connection>MBlaze USB Modem</connection>
      <since>2013-07-09 11:04:22</since>
      <duration>1889</duration>
      <in>10110164</in>
      <out>2519282</out>
    </item>
    <item>
      <connection>MBlaze USB Modem</connection>
      <since>2013-07-09 19:56:47</since>
      <duration>7660</duration>
      <in>48172251</in>
      <out>8045102</out>
    </item>
    <item>
      <connection>MBlaze USB Modem</connection>
      <since>2013-07-09 22:46:43</since>
      <duration>3126</duration>
      <in>6457800</in>
      <out>1080831</out>
    </item>
    <item>
      <connection>MBlaze USB Modem</connection>
      <since>2013-07-10 10:41:52</since>
      <duration>5985</duration>
      <in>29768809</in>
      <out>4815178</out>
    </item>
    <item>
      <connection>MBlaze USB Modem</connection>
      <since>2013-07-10 13:07:15</since>
      <duration>1670</duration>
      <in>7363104</in>
      <out>2666098</out>
    </item>
    <item>
      <connection>MBlaze USB Modem</connection>
      <since>2013-07-10 14:49:41</since>
      <duration>1370</duration>
      <in>7624764</in>
      <out>1260769</out>
    </item>
    <item>
      <connection>MBlaze USB Modem</connection>
      <since>2013-07-10 18:55:45</since>
      <duration>6388</duration>
      <in>68599764</in>
      <out>8340589</out>
    </item>
    <item>
      <connection>MBlaze USB Modem</connection>
      <since>2013-07-11 12:38:56</since>
      <duration>952</duration>
      <in>8834074</in>
      <out>1370762</out>
    </item>
    <item>
      <connection>MBlaze USB Modem</connection>
      <since>2013-07-11 13:06:24</since>
      <duration>7373</duration>
      <in>19829408</in>
      <out>3600236</out>
    </item>
    <item>
      <connection>MBlaze USB Modem</connection>
      <since>2013-07-11 15:09:25</since>
      <duration>587</duration>
      <in>4498114</in>
      <out>818169</out>
    </item>
    <item>
      <connection>MBlaze USB Modem</connection>
      <since>2013-07-11 16:15:30</since>
      <duration>6745</duration>
      <in>65138987</in>
      <out>8836242</out>
    </item>
    <item>
      <connection>MBlaze USB Modem</connection>
      <since>2013-07-12 12:43:35</since>
      <duration>1219</duration>
      <in>31687760</in>
      <out>2556314</out>
    </item>
    <item>
      <connection>MBlaze USB Modem</connection>
      <since>2013-07-12 14:31:24</since>
      <duration>4015</duration>
      <in>44951460</in>
      <out>10719892</out>
    </item>
    <item>
      <connection>MBlaze USB Modem</connection>
      <since>2013-07-12 17:25:52</since>
      <duration>1398</duration>
      <in>16113378</in>
      <out>2615924</out>
    </item>
    <item>
      <connection>MBlaze USB Modem</connection>
      <since>2013-07-12 20:32:25</since>
      <duration>10401</duration>
      <in>105381042</in>
      <out>19410555</out>
    </item>
    <item>
      <connection>MBlaze USB Modem</connection>
      <since>2013-07-16 20:06:13</since>
      <duration>2123</duration>
      <in>23217008</in>
      <out>3598783</out>
    </item>
    <item>
      <connection>MBlaze USB Modem</connection>
      <since>2013-07-16 20:41:56</since>
      <duration>2738</duration>
      <in>33730066</in>
      <out>2287783</out>
    </item>
    <item>
      <connection>MBlaze USB Modem</connection>
      <since>2013-07-16 21:27:54</since>
      <duration>7385</duration>
      <in>19122843</in>
      <out>3889081</out>
    </item>
    <item>
      <connection>MBlaze USB Modem</connection>
      <since>2013-07-17 20:14:23</since>
      <duration>8211</duration>
      <in>31999213</in>
      <out>4601726</out>
    </item>
    <item>
      <connection>MBlaze USB Modem</connection>
      <since>2013-07-17 22:31:30</since>
      <duration>2648</duration>
      <in>16772822</in>
      <out>3429609</out>
    </item>
    <item>
      <connection>MBlaze USB Modem</connection>
      <since>2013-07-18 16:16:39</since>
      <duration>6275</duration>
      <in>32923685</in>
      <out>2853397</out>
    </item>
    <item>
      <connection>MBlaze USB Modem</connection>
      <since>2013-07-18 18:06:51</since>
      <duration>4222</duration>
      <in>36082623</in>
      <out>4374063</out>
    </item>
    <item>
      <connection>MBlaze USB Modem</connection>
      <since>2013-07-18 20:10:05</since>
      <duration>5198</duration>
      <in>41451548</in>
      <out>3202724</out>
    </item>
    <item>
      <connection>MBlaze USB Modem</connection>
      <since>2013-07-19 16:03:06</since>
      <duration>119</duration>
      <in>942796</in>
      <out>142617</out>
    </item>
    <item>
      <connection>MBlaze USB Modem</connection>
      <since>2013-07-19 16:05:10</since>
      <duration>8070</duration>
      <in>36127092</in>
      <out>4849240</out>
    </item>
    <item>
      <connection>MBlaze USB Modem</connection>
      <since>2013-07-19 19:13:24</since>
      <duration>20</duration>
      <in>396706</in>
      <out>97457</out>
    </item>
    <item>
      <connection>MBlaze USB Modem</connection>
      <since>2013-07-19 21:07:38</since>
      <duration>16395</duration>
      <in>86193712</in>
      <out>16307376</out>
    </item>
    <item>
      <connection>MBlaze USB Modem</connection>
      <since>2013-07-20 12:30:08</since>
      <duration>19568</duration>
      <in>22061524</in>
      <out>3990977</out>
    </item>
    <item>
      <connection>MBlaze USB Modem</connection>
      <since>2013-07-21 10:20:22</since>
      <duration>13588</duration>
      <in>42408164</in>
      <out>4652190</out>
    </item>
    <item>
      <connection>MBlaze USB Modem</connection>
      <since>2013-07-21 17:00:36</since>
      <duration>2304</duration>
      <in>1786250</in>
      <out>312631</out>
    </item>
    <item>
      <connection>MBlaze USB Modem</connection>
      <since>2013-07-21 19:57:52</since>
      <duration>5682</duration>
      <in>22906637</in>
      <out>4011303</out>
    </item>
    <item>
      <connection>MBlaze USB Modem</connection>
      <since>2013-07-22 16:40:35</since>
      <duration>9009</duration>
      <in>45820425</in>
      <out>5150460</out>
    </item>
    <item>
      <connection>MBlaze USB Modem</connection>
      <since>2013-07-23 17:26:31</since>
      <duration>6743</duration>
      <in>34897534</in>
      <out>3394627</out>
    </item>
    <item>
      <connection>MBlaze USB Modem</connection>
      <since>2013-07-23 20:20:50</since>
      <duration>9626</duration>
      <in>45066577</in>
      <out>8351964</out>
    </item>
    <item>
      <connection>MBlaze USB Modem</connection>
      <since>2013-07-23 23:45:18</since>
      <duration>502</duration>
      <in>7977452</in>
      <out>1319161</out>
    </item>
    <item>
      <connection>MBlaze USB Modem</connection>
      <since>2013-07-24 20:13:01</since>
      <duration>9150</duration>
      <in>83773919</in>
      <out>7595227</out>
    </item>
    <item>
      <connection>MBlaze USB Modem</connection>
      <since>2013-07-25 17:33:41</since>
      <duration>6083</duration>
      <in>30631472</in>
      <out>3868667</out>
    </item>
    <item>
      <connection>MBlaze USB Modem</connection>
      <since>2013-07-25 20:54:51</since>
      <duration>6776</duration>
      <in>110384907</in>
      <out>7167458</out>
    </item>
    <item>
      <connection>MBlaze USB Modem</connection>
      <since>2013-07-29 18:05:37</since>
      <duration>66</duration>
      <in>1314</in>
      <out>60535</out>
    </item>
    <item>
      <connection>MBlaze USB Modem</connection>
      <since>2013-07-29 18:09:13</since>
      <duration>679</duration>
      <in>50984</in>
      <out>112419</out>
    </item>
  </dialup>
</networx-backup>
